bae0n_utils/FeatureCorrelation.py
bae0n_utils/ImageUtils.py
bae0n_utils/OSUtils.py
bae0n_utils/__init__.py
bae0n_utils-0.1.2.dist-info/LICENSE
bae0n_utils-0.1.2.dist-info/METADATA
bae0n_utils-0.1.2.dist-info/WHEEL
bae0n_utils-0.1.2.dist-info/top_level.txt
bae0n_utils-0.1.2.dist-info/RECORD
