Metadata-Version: 2.1
Name: bae0n-utils
Version: 0.1.2
Summary: Utility functions to be used in Python
Home-page: https://github.com/aeonwilliams/bae0n_utils/blob/main/README.md
Author: Aeon Williams
Author-email: aeonwilliams@gmail.com
License: UNKNOWN
Platform: UNKNOWN
Classifier: Programming Language :: Python :: 3
Classifier: License :: OSI Approved :: MIT License
Classifier: Operating System :: OS Independent
Requires-Python: >=3
Requires-Dist: Pillow
Requires-Dist: numpy
Requires-Dist: pandas
Requires-Dist: pathlib
